ament_cmake_export_libraries/_dummy.cpython-313-x86_64-linux-gnu.so
ros_ament_cmake_export_libraries-2.7.3.data/data/share/ament_cmake_export_libraries/local_setup.bash
ros_ament_cmake_export_libraries-2.7.3.data/data/share/ament_cmake_export_libraries/local_setup.dsv
ros_ament_cmake_export_libraries-2.7.3.data/data/share/ament_cmake_export_libraries/local_setup.sh
ros_ament_cmake_export_libraries-2.7.3.data/data/share/ament_cmake_export_libraries/local_setup.zsh
ros_ament_cmake_export_libraries-2.7.3.data/data/share/ament_cmake_export_libraries/package.dsv
ros_ament_cmake_export_libraries-2.7.3.data/data/share/ament_cmake_export_libraries/package.xml
ros_ament_cmake_export_libraries-2.7.3.data/data/share/ament_cmake_export_libraries/cmake/ament_cmake_export_libraries-extras.cmake
ros_ament_cmake_export_libraries-2.7.3.data/data/share/ament_cmake_export_libraries/cmake/ament_cmake_export_libraries-extras.cmake.in
ros_ament_cmake_export_libraries-2.7.3.data/data/share/ament_cmake_export_libraries/cmake/ament_cmake_export_librariesConfig-version.cmake
ros_ament_cmake_export_libraries-2.7.3.data/data/share/ament_cmake_export_libraries/cmake/ament_cmake_export_librariesConfig.cmake
ros_ament_cmake_export_libraries-2.7.3.data/data/share/ament_cmake_export_libraries/cmake/ament_cmake_export_libraries_package_hook.cmake
ros_ament_cmake_export_libraries-2.7.3.data/data/share/ament_cmake_export_libraries/cmake/ament_export_libraries.cmake
ros_ament_cmake_export_libraries-2.7.3.data/data/share/ament_cmake_export_libraries/cmake/ament_export_library_names.cmake
ros_ament_cmake_export_libraries-2.7.3.data/data/share/ament_cmake_export_libraries/environment/ament_prefix_path.dsv
ros_ament_cmake_export_libraries-2.7.3.data/data/share/ament_cmake_export_libraries/environment/ament_prefix_path.sh
ros_ament_cmake_export_libraries-2.7.3.data/data/share/ament_cmake_export_libraries/environment/path.dsv
ros_ament_cmake_export_libraries-2.7.3.dist-info/METADATA
ros_ament_cmake_export_libraries-2.7.3.dist-info/WHEEL
ros_ament_cmake_export_libraries-2.7.3.dist-info/top_level.txt
ros_ament_cmake_export_libraries-2.7.3.dist-info/RECORD
