Metadata-Version: 2.4
Name: ros-ament-cmake-export-libraries
Version: 2.7.3
Summary: Wheel for the ament_cmake_export_libraries (ros-ament-cmake-export-libraries) ROS 2 package.
Dynamic: description
Dynamic: description-content-type
Dynamic: summary
